MANIFEST.in
README.md
pyproject.toml
setup.cfg
setup.py
django_generic_delete.egg-info/PKG-INFO
django_generic_delete.egg-info/SOURCES.txt
django_generic_delete.egg-info/dependency_links.txt
django_generic_delete.egg-info/top_level.txt
softdelete/__init__.py
softdelete/admin.py
softdelete/apps.py
softdelete/models.py
softdelete/urls.py
softdelete/views.py
softdelete/migrations/__init__.py
softdelete/templates/softdelete/delete_confirmation.html
softdelete/tests/__init__.py
softdelete/tests/models.py
softdelete/tests/test_soft_deletion_model.py
softdelete/tests/test_soft_deletion_view.py